huaweicloudsdkcdm/__init__.py
huaweicloudsdkcdm/v1/__init__.py
huaweicloudsdkcdm/v1/cdm_async_client.py
huaweicloudsdkcdm/v1/cdm_client.py
huaweicloudsdkcdm/v1/model/__init__.py
huaweicloudsdkcdm/v1/model/action_progress.py
huaweicloudsdkcdm/v1/model/cdm_cluster_availability_zone.py
huaweicloudsdkcdm/v1/model/cdm_cluster_datastore.py
huaweicloudsdkcdm/v1/model/cdm_cluster_datastore_version.py
huaweicloudsdkcdm/v1/model/cdm_cluster_enterprise_project.py
huaweicloudsdkcdm/v1/model/cdm_cluster_flavor.py
huaweicloudsdkcdm/v1/model/cdm_cluster_version.py
huaweicloudsdkcdm/v1/model/cdm_create_and_update_link_req.py
huaweicloudsdkcdm/v1/model/cdm_create_cluster_req.py
huaweicloudsdkcdm/v1/model/cdm_create_cluster_req_cluster.py
huaweicloudsdkcdm/v1/model/cdm_create_job_json_req.py
huaweicloudsdkcdm/v1/model/cdm_delete_cluster_req.py
huaweicloudsdkcdm/v1/model/cdm_modify_cluster_req.py
huaweicloudsdkcdm/v1/model/cdm_query_cluster_details_repsonse_maintain_window.py
huaweicloudsdkcdm/v1/model/cdm_query_cluster_details_repsonse_public_endpoint_status.py
huaweicloudsdkcdm/v1/model/cdm_query_cluster_instance_detail.py
huaweicloudsdkcdm/v1/model/cdm_query_cluster_instance_detail_flavor.py
huaweicloudsdkcdm/v1/model/cdm_random_create_and_start_job_json_req.py
huaweicloudsdkcdm/v1/model/cdm_restart_cluster_req.py
huaweicloudsdkcdm/v1/model/cdm_restart_cluster_req_restart.py
huaweicloudsdkcdm/v1/model/cdm_start_cluster_req.py
huaweicloudsdkcdm/v1/model/cdm_start_job_req.py
huaweicloudsdkcdm/v1/model/cdm_stop_cluster_req.py
huaweicloudsdkcdm/v1/model/cdm_stop_cluster_req_stop.py
huaweicloudsdkcdm/v1/model/cdm_update_job_json_req.py
huaweicloudsdkcdm/v1/model/cluster_detail_instance.py
huaweicloudsdkcdm/v1/model/cluster_detail_instance_flavor.py
huaweicloudsdkcdm/v1/model/cluster_detail_instance_volume.py
huaweicloudsdkcdm/v1/model/cluster_instance.py
huaweicloudsdkcdm/v1/model/cluster_links.py
huaweicloudsdkcdm/v1/model/cluster_task.py
huaweicloudsdkcdm/v1/model/clusters.py
huaweicloudsdkcdm-3.1.184.dist-info/METADATA
huaweicloudsdkcdm-3.1.184.dist-info/WHEEL
huaweicloudsdkcdm-3.1.184.dist-info/licenses/LICENSE
huaweicloudsdkcdm-3.1.184.dist-info/RECORD
