Metadata-Version: 2.4
Name: huaweicloudsdkcdm
Version: 3.1.184
Summary: CDM
Project-URL: Homepage, https://github.com/huaweicloud/huaweicloud-sdk-python-v3
Author-email: HuaweiCloud SDK <hwcloudsdk@huawei.com>
License-Expression: Apache-2.0
License-File: LICENSE
Keywords: CDM,huaweicloud,sdk
Classifier: Development Status :: 5 - Production/Stable
Classifier: Intended Audience :: Developers
Classifier: License :: OSI Approved :: Apache Software License
Classifier: Programming Language :: Python :: 3.6
Classifier: Programming Language :: Python :: 3.7
Classifier: Programming Language :: Python :: 3.8
Classifier: Programming Language :: Python :: 3.9
Classifier: Programming Language :: Python :: 3.10
Classifier: Programming Language :: Python :: 3.11
Classifier: Programming Language :: Python :: 3.12
Classifier: Topic :: Software Development
Requires-Python: >=3.6
Requires-Dist: huaweicloudsdkcore>=3.1.184
